Workbook

Sheet P&L
A1: DeepDesk — Profit & Loss (Build with Gemini XPRIZE, May 19 – Aug 17, 2026)
A2: All figures in USD. Business launched Aug 12, 2026. Blue cells = inputs to update as sales occur.
A4: FX assumption (KRW per USD) | B4: 1380 | C4: Source: market rate 2026-08, user to update at submission
B6: May 2026 | C6: Jun 2026 | D6: Jul 2026 | E6: Aug 2026 | F6: Total
A7: Gross revenue (KRW) | B7: 0 | C7: 0 | D7: 0 | E7: 0 | F7: =SUM(B7:E7) -> 0
A8: Gross revenue (USD) | B8: =B7/$B$4 -> 0 | C8: =C7/$B$4 -> 0 | D8: =D7/$B$4 -> 0 | E8: =E7/$B$4 -> 0 | F8: =SUM(B8:E8) -> 0
A9: of which related-party (USD) | B9: 0 | C9: 0 | D9: 0 | E9: 0 | F9: =SUM(B9:E9) -> 0
A10: Payment processing fees | B10: =-B8*$B$20 -> 0 | C10: =-C8*$B$20 -> 0 | D10: =-D8*$B$20 -> 0 | E10: =-E8*$B$20 -> 0 | F10: =SUM(B10:E10) -> 0
A11: Net revenue | B11: =B8+B10 -> 0 | C11: =C8+C10 -> 0 | D11: =D8+D10 -> 0 | E11: =E8+E10 -> 0 | F11: =SUM(B11:E11) -> 0
A12: COGS — LLM inference | B12: 0 | C12: 0 | D12: 0 | E12: =-'Cost Detail'!F10 -> -0.728133 | F12: =SUM(B12:E12) -> -0.728133
A13: COGS — paid data (agent USDC) | B13: 0 | C13: 0 | D13: 0 | E13: =-'Cost Detail'!G10 -> 0 | F13: =SUM(B13:E13) -> 0
A14: Gross profit | B14: =B11+B12+B13 -> 0 | C14: =C11+C12+C13 -> 0 | D14: =D11+D12+D13 -> 0 | E14: =E11+E12+E13 -> -0.728133 | F14: =SUM(B14:E14) -> -0.728133
A15: Infra — Google Cloud Run/Build | B15: 0 | C15: 0 | D15: 0 | E15: -4 | F15: =SUM(B15:E15) -> -4
A16: Marketing & customer acquisition | B16: 0 | C16: 0 | D16: 0 | E16: 0 | F16: =SUM(B16:E16) -> 0
A17: Net income | B17: =B14+B15+B16 -> 0 | C17: =C14+C15+C16 -> 0 | D17: =D14+D15+D16 -> 0 | E17: =E14+E15+E16 -> -4.728133 | F17: =SUM(B17:E17) -> -4.728133
A19: Infra note: Cloud Run min-instance from Aug 12 (~$0.35/day, 512Mi always-on) + Cloud Build; Firestore within free tier. Estimate marked as input.
A20: Toss Payments fee rate | B20: 0.033 | C20: Card widget standard rate incl. VAT (tosspayments.com pricing)
A21: Unit economics (per report, actuals)
A22: Tier | B22: Price (KRW) | C22: Price (USD) | D22: Avg LLM cost (USD) | E22: Gross margin
A23: light | B23: 4900 | C23: =B23/$B$4 -> 3.5507246 | D23: =IFERROR(AVERAGEIF('Cost Detail'!C:C,A23,'Cost Detail'!F:F),0) -> 0.090705 | E23: =IFERROR((C23-D23)/C23,0) -> 0.97445451
A24: standard | B24: 14900 | C24: =B24/$B$4 -> 10.797101 | D24: =IFERROR(AVERAGEIF('Cost Detail'!C:C,A24,'Cost Detail'!F:F),0) -> 0 | E24: =IFERROR((C24-D24)/C24,0) -> 1
A25: deep | B25: 29900 | C25: =B25/$B$4 -> 21.666667 | D25: =IFERROR(AVERAGEIF('Cost Detail'!C:C,A25,'Cost Detail'!F:F),0) -> 0.456018 | E25: =IFERROR((C25-D25)/C25,0) -> 0.97895302
A28: Legend: BLUE = input cells (update with actual sales) · BLACK = formulas · GREEN = links to Cost Detail sheet · YELLOW fill = key assumptions

Sheet Cost Detail
A1: DeepDesk — Actual Run Cost Detail (hackathon period)
A3: Blended LLM token price (USD per 1M tokens) | B3: 3 | C3: Assumption: mix of gemini-2.5-flash ($0.30/$2.50 per 1M in/out) and gemini-2.5-pro ($1.25/$10). $3/1M blended is conservative. Source: ai.google.dev/pricing (2026-08).
A5: Order ID | B5: Date (UTC) | C5: Tier | D5: Status | E5: LLM tokens | F5: LLM cost (USD) | G5: Paid data USDC (testnet, $ real value)
A6: 10565882 | B6: 2026-08-11 | C6: light | D6: done | E6: 26857 | F6: =E6/1000000*$B$3 -> 0.080571 | G6: 0
A7: 56cc04bc | B7: 2026-08-11 | C7: light | D7: done | E7: 28161 | F7: =E7/1000000*$B$3 -> 0.084483 | G7: 0
A8: 018ea42c | B8: 2026-08-11 | C8: light | D8: done | E8: 35687 | F8: =E8/1000000*$B$3 -> 0.107061 | G8: 0
A9: f3949e85 | B9: 2026-08-12 | C9: deep | D9: done | E9: 152006 | F9: =E9/1000000*$B$3 -> 0.456018 | G9: 0
D10: TOTAL | E10: =SUM(E6:E9) -> 242711 | F10: =SUM(F6:F9) -> 0.728133 | G10: =SUM(G6:G9) -> 0
A12: Note: agent paid-data settlements run on Base Sepolia testnet USDC (no real monetary value in pilot); on-chain records: sepolia.basescan.org/address/0x6d721e3d036695e4be921af1b3e5d3a8502ff698
